torchvision_extra/__init__.py
torchvision_extra/datasets/__init__.py
torchvision_extra/datasets/oxford_iiit_pet_plus.py
torchvision_extra/datasets/stack.py
torchvision_extra/datasets/stanford_dogs.py
torchvision_extra/models/__init__.py
torchvision_extra/models/detection/__init__.py
torchvision_extra/models/detection/faster_rcnn.py
torchvision_extra/transforms/__init__.py
torchvision_extra/transforms/compose.py
torchvision_extra/transforms/dict_transforms.py
torchvision_extra/transforms/to_tensors.py
torchvision_extra/utils/__init__.py
torchvision_extra/utils/vocabulary.py
torchvision_extra-0.0.17.dist-info/LICENSE
torchvision_extra-0.0.17.dist-info/METADATA
torchvision_extra-0.0.17.dist-info/WHEEL
torchvision_extra-0.0.17.dist-info/top_level.txt
torchvision_extra-0.0.17.dist-info/RECORD
