Metadata-Version: 2.1
Name: torchvision-extra
Version: 0.0.17
Summary: Additional datasets compatible with torchvision format
Home-page: UNKNOWN
Author: Chenchao Zhao
Author-email: chenchao.zhao@gmail.com
License: MIT
Platform: UNKNOWN
License-File: LICENSE
Requires-Dist: torch
Requires-Dist: numpy
Requires-Dist: torchvision
Requires-Dist: pillow
